cursofiap/__init__.py
cursofiap/core.py
cursofiap33_package-1.0.0.dist-info/METADATA
cursofiap33_package-1.0.0.dist-info/WHEEL
cursofiap33_package-1.0.0.dist-info/top_level.txt
cursofiap33_package-1.0.0.dist-info/RECORD
